CHANGES
LICENSE
MANIFEST.in
setup.cfg
setup.py
mazingame/__init__.py
mazingame/__main__.py
mazingame/gameclasses.py
mazingame/globals.py
mazingame/highscores.py
mazingame/mazingame.py
mazingame.egg-info/PKG-INFO
mazingame.egg-info/SOURCES.txt
mazingame.egg-info/dependency_links.txt
mazingame.egg-info/entry_points.txt
mazingame.egg-info/requires.txt
mazingame.egg-info/top_level.txt
mazingame/utils/__init__.py
mazingame/utils/utils.py