Metadata-Version: 1.1
Name: mazingame
Version: 1.4.1
Summary: A game of maze.
Home-page: https://github.com/samisalkosuo/mazingame
Author: Sami Salkosuo
Author-email: dev@rnd-dev.com
License: MIT
Platform: UNKNOWN
Classifier: Environment :: Console :: Curses
Classifier: License :: OSI Approved :: MIT License
Classifier: Natural Language :: English
Classifier: Topic :: Games/Entertainment
Classifier: Programming Language :: Python :: 3.4
Classifier: Programming Language :: Python :: 3.5
Classifier: Programming Language :: Python :: 3 :: Only
